yulewalker/__init__.py
yulewalker/yulewalker.py
yulewalker-0.1.1.dist-info/LICENSE
yulewalker-0.1.1.dist-info/METADATA
yulewalker-0.1.1.dist-info/WHEEL
yulewalker-0.1.1.dist-info/top_level.txt
yulewalker-0.1.1.dist-info/RECORD
