Metadata-Version: 2.1
Name: yulewalker
Version: 0.1.1
Summary: IIR Filter design using the modified Yule-Walker method
Home-page: UNKNOWN
Author: Emmanouil Theofanis Chourdakis
Author-email: emmanouil.chourdakis@nomono.co
License: CeCILL-2.1
Keywords: yulewalk yulewalker iir signal-processing dsp
Platform: UNKNOWN
Classifier: Topic :: Scientific/Engineering
Classifier: Development Status :: 3 - Alpha
Classifier: License :: OSI Approved :: CEA CNRS Inria Logiciel Libre License, version 2.1 (CeCILL-2.1)
Requires-Dist: numpy (>=1.19.2)
Requires-Dist: scipy (>=1.5.2)
